riffusion/__init__.py
riffusion/audio_splitter.py
riffusion/cli.py
riffusion/datatypes.py
riffusion/external/README.md
riffusion/external/__init__.py
riffusion/external/prompt_weighting.py
riffusion/playground.py
riffusion/riffusion_pipeline.py
riffusion/server.py
riffusion/spectrogram_converter.py
riffusion/spectrogram_image_converter.py
riffusion/spectrogram_params.py
riffusion/streamlit/README.md
riffusion/streamlit/__init__.py
riffusion/streamlit/pages/audio_to_audio.py
riffusion/streamlit/pages/image_to_audio.py
riffusion/streamlit/pages/interpolation.py
riffusion/streamlit/pages/sample_clips.py
riffusion/streamlit/pages/split_audio.py
riffusion/streamlit/pages/text_to_audio.py
riffusion/streamlit/pages/text_to_audio_batch.py
riffusion/streamlit/playground.py
riffusion/streamlit/util.py
riffusion/util/__init__.py
riffusion/util/audio_util.py
riffusion/util/base64_util.py
riffusion/util/fft_util.py
riffusion/util/image_util.py
riffusion/util/torch_util.py
riffusion-0.0.5.dist-info/LICENSE
riffusion-0.0.5.dist-info/WHEEL
riffusion-0.0.5.dist-info/entry_points.txt
riffusion-0.0.5.dist-info/METADATA
riffusion-0.0.5.dist-info/RECORD
