Metadata-Version: 2.1
Name: riffusion
Version: 0.0.5
Summary: Stable diffusion for real-time music generation.
License: MIT
Author: Hayk Martiros
Author-email: hayk.mart@gmail.com
Requires-Python: >=3.8, !=2.7.*, !=3.0.*, !=3.1.*, !=3.2.*, !=3.3.*, !=3.4.*, !=3.5.*, !=3.6.*, !=3.7.*
Classifier: License :: OSI Approved :: MIT License
Classifier: Programming Language :: Python :: 3
Classifier: Programming Language :: Python :: 3.9
Classifier: Programming Language :: Python :: 3.10
Classifier: Programming Language :: Python :: 3.11
Requires-Dist: accelerate (>=0.16.0,<0.17.0)
Requires-Dist: argh (>=0.27.2,<0.28.0)
Requires-Dist: dacite (>=1.8.0,<2.0.0)
Requires-Dist: demucs (>=4.0.0,<5.0.0)
Requires-Dist: diffusers (>=0.9.0)
Requires-Dist: flask (>=2.2.2,<3.0.0)
Requires-Dist: flask-cors (>=3.0.10,<4.0.0)
Requires-Dist: numpy (>=1.24.2,<2.0.0)
Requires-Dist: pillow (>=9.4.0,<10.0.0)
Requires-Dist: plotly (>=5.13.0,<6.0.0)
Requires-Dist: pydub (>=0.25.1,<0.26.0)
Requires-Dist: pysoundfile (>=0.9.0.post1,<0.10.0)
Requires-Dist: scipy (>=1.10.0,<2.0.0)
Requires-Dist: soundfile (>=0.11.0,<0.12.0)
Requires-Dist: sox (>=1.4.1,<2.0.0)
Requires-Dist: streamlit (>=1.17.0,<1.18.0)
Requires-Dist: torch (>=1.13.1,<2.0.0)
Requires-Dist: torchaudio (>=0.13.1,<0.14.0)
Requires-Dist: torchvision (>=0.14.1,<0.15.0)
Requires-Dist: transformers (>=4.26.1,<5.0.0)
Requires-Dist: watchdog (>=2.3.0,<3.0.0)
